kanby/__init__.py
kanby/async_save.py
kanby/main.py
kanby/message_system.py
kanby-1.0.23.dist-info/licenses/LICENSE
kanby-1.0.23.dist-info/METADATA
kanby-1.0.23.dist-info/WHEEL
kanby-1.0.23.dist-info/entry_points.txt
kanby-1.0.23.dist-info/top_level.txt
kanby-1.0.23.dist-info/RECORD
