Metadata-Version: 2.4
Name: kanby
Version: 1.0.23
Summary: A beautiful terminal-based Kanban board
Author-email: Vlad Arbatov <vlad@arbatov.dev>
License: MIT
Project-URL: Homepage, https://github.com/vladzima/kanby
Project-URL: Repository, https://github.com/vladzima/kanby
Project-URL: Issues, https://github.com/vladzima/kanby/issues
Keywords: kanban,terminal,productivity,todo,curses,cli
Classifier: Development Status :: 4 - Beta
Classifier: Environment :: Console :: Curses
Classifier: Intended Audience :: Developers
Classifier: Intended Audience :: End Users/Desktop
Classifier: License :: OSI Approved :: MIT License
Classifier: Operating System :: OS Independent
Classifier: Programming Language :: Python :: 3
Classifier: Programming Language :: Python :: 3.7
Classifier: Programming Language :: Python :: 3.8
Classifier: Programming Language :: Python :: 3.9
Classifier: Programming Language :: Python :: 3.10
Classifier: Programming Language :: Python :: 3.11
Classifier: Programming Language :: Python :: 3.12
Classifier: Topic :: Office/Business
Classifier: Topic :: Software Development :: Bug Tracking
Classifier: Topic :: Terminals
Classifier: Topic :: Utilities
Requires-Python: >=3.7
License-File: LICENSE
Requires-Dist: windows-curses; sys_platform == "win32"
Dynamic: license-file
